[
  {
    "count": 1,
    "name": "Casual",
    "category": [
      "Gamemodes"
    ],
    "progression": true
  },
  {
    "count": 1,
    "name": "Intermediate",
    "category": [
      "Gamemodes"
    ],
    "progression": true
  },
  {
    "count": 1,
    "name": "Molten",
    "category": [
      "Gamemodes"
    ],
    "progression": true
  },
  {
    "count": 1,
    "name": "Fallen",
    "category": [
      "Gamemodes"
    ],
    "progression": true
  },
  {
    "count": 1,
    "name": "Frost",
    "category": [
      "Gamemodes"
    ],
    "progression": true
  },
  {
    "count": 1,
    "name": "Golden Scout",
    "category": [
      "Golden Perks"
    ],
    "useful": true
  },
  {
    "count": 1,
    "name": "Soldier",
    "category": [
      "Towers",
      "Starter Towers"
    ],
    "useful": true
  },
  {
    "count": 1,
    "name": "Golden Soldier",
    "category": [
      "Golden Perks"
    ],
    "useful": true
  },
  {
    "count": 1,
    "name": "Paintballer",
    "category": [
      "Towers",
      "Starter Towers"
    ],
    "useful": true
  },
  {
    "count": 1,
    "name": "Demoman",
    "category": [
      "Towers",
      "Starter Towers"
    ],
    "useful": true
  },
  {
    "count": 1,
    "name": "Hunter",
    "category": [
      "Towers",
      "Starter Towers"
    ],
    "useful": true
  },
  {
    "count": 1,
    "name": "Militant",
    "category": [
      "Towers",
      "Starter Towers"
    ],
    "useful": true
  },
  {
    "count": 1,
    "name": "Crook Boss",
    "category": [
      "Towers",
      "Intermediate Towers"
    ],
    "useful": true
  },
  {
    "count": 1,
    "name": "Golden Crook Boss",
    "category": [
      "Golden Perks"
    ],
    "useful": true
  },
  {
    "count": 1,
    "name": "Pyromancer",
    "category": [
      "Towers",
      "Intermediate Towers"
    ],
    "useful": true
  },
  {
    "count": 1,
    "name": "Golden Pyromancer",
    "category": [
      "Golden Perks"
    ],
    "useful": true
  },
  {
    "count": 1,
    "name": "Freezer",
    "category": [
      "Towers",
      "Intermediate Towers"
    ],
    "useful": true
  },
  {
    "count": 1,
    "name": "Assassin",
    "category": [
      "Towers",
      "Intermediate Towers"
    ],
    "useful": true
  },
  {
    "count": 1,
    "name": "Shotgunner",
    "category": [
      "Towers",
      "Intermediate Towers"
    ],
    "useful": true
  },
  {
    "count": 1,
    "name": "Ace Pilot",
    "category": [
      "Towers",
      "Intermediate Towers"
    ],
    "useful": true
  },
  {
    "count": 1,
    "name": "Medic",
    "category": [
      "Towers",
      "Intermediate Towers"
    ],
    "useful": true
  },
  {
    "count": 1,
    "name": "Farm",
    "category": [
      "Towers",
      "Intermediate Towers"
    ],
    "useful": true
  },
  {
    "count": 1,
    "name": "Trapper",
    "category": [
      "Towers",
      "Intermediate Towers"
    ],
    "useful": true
  },
  {
    "count": 1,
    "name": "Rocketeer",
    "category": [
      "Towers",
      "Intermediate Towers"
    ],
    "useful": true
  },
  {
    "count": 1,
    "name": "Military Base",
    "category": [
      "Towers",
      "Intermediate Towers"
    ],
    "useful": true
  },
  {
    "count": 1,
    "name": "Cowboy",
    "category": [
      "Towers",
      "Advanced Towers"
    ],
    "useful": true
  },
  {
    "count": 1,
    "name": "Golden Cowboy",
    "category": [
      "Golden Perks"
    ],
    "useful": true
  },
  {
    "count": 1,
    "name": "Minigunner",
    "category": [
      "Towers",
      "Advanced Towers"
    ],
    "useful": true
  },
  {
    "count": 1,
    "name": "Golden Minigunner",
    "category": [
      "Golden Perks"
    ],
    "useful": true
  },
  {
    "count": 1,
    "name": "Mortar",
    "category": [
      "Towers",
      "Advanced Towers"
    ],
    "useful": true
  },
  {
    "count": 1,
    "name": "Turret",
    "category": [
      "Towers",
      "Advanced Towers"
    ],
    "useful": true
  },
  {
    "count": 1,
    "name": "Merc base",
    "category": [
      "Towers",
      "Advanced Towers"
    ],
    "useful": true
  },
  {
    "count": 1,
    "name": "Electroshocker",
    "category": [
      "Towers",
      "Advanced Towers"
    ],
    "useful": true
  },
  {
    "count": 1,
    "name": "Warden",
    "category": [
      "Towers",
      "Advanced Towers"
    ],
    "useful": true
  },
  {
    "count": 1,
    "name": "Commander",
    "category": [
      "Towers",
      "Advanced Towers"
    ],
    "useful": true
  },
  {
    "count": 1,
    "name": "DJ Booth",
    "category": [
      "Towers",
      "Advanced Towers"
    ],
    "useful": true
  },
  {
    "count": 1,
    "name": "Ranger",
    "category": [
      "Towers",
      "Advanced Towers"
    ],
    "useful": true
  },
  {
    "count": 1,
    "name": "Pursuit",
    "category": [
      "Towers",
      "Advanced Towers"
    ],
    "useful": true
  },
  {
    "count": 1,
    "name": "Gatling Gun",
    "category": [
      "Towers",
      "Advanced Towers"
    ],
    "useful": true
  },
  {
    "count": 1,
    "name": "Brawler",
    "category": [
      "Towers",
      "Hardcore Towers"
    ],
    "useful": true
  },
  {
    "count": 1,
    "name": "Necromancer",
    "category": [
      "Towers",
      "Hardcore Towers"
    ],
    "useful": true
  },
  {
    "count": 1,
    "name": "Accelerator",
    "category": [
      "Towers",
      "Hardcore Towers"
    ],
    "useful": true
  },
  {
    "count": 1,
    "name": "Engineer",
    "category": [
      "Towers",
      "Hardcore Towers"
    ],
    "useful": true
  },
  {
    "count": 1,
    "name": "Hacker",
    "category": [
      "Towers",
      "Hardcore Towers"
    ],
    "useful": true
  },
  {
    "count": 1,
    "name": "Skill Tree",
    "category": [
      "Features"
      "Skill Tree"
    ],
    "useful": true
  },
  {
    "count": 1,
    "name": "Jester",
    "category": [
      "Towers",
      "Exclusive Towers"
    ],
    "useful": true
  },
  {
    "count": 1,
    "name": "Harvester",
    "category": [
      "Towers",
      "Exclusive Towers"
    ],
    "useful": true
  },
  {
    "count": 1,
    "name": "Elementalist",
    "category": [
      "Towers",
      "Exclusive Towers"
    ],
    "useful": true
  },
  {
    "count": 1,
    "name": "Biologist",
    "category": [
      "Towers",
      "Exclusive Towers"
    ],
    "useful": true
  },
  {
    "count": 1,
    "name": "Snowballer",
    "category": [
      "Towers",
      "Exclusive Towers"
    ],
    "useful": true
  },
  {
    "count": 1,
    "name": "Firework Tech",
    "category": [
      "Towers",
      "Exclusive Towers"
    ],
    "useful": true
  },
  {
    "count": 1,
    "name": "Gladiator",
    "category": [
      "Towers",
      "Exclusive Towers"
    ],
    "useful": true
  },
  {
    "count": 1,
    "name": "Hallow Punk",
    "category": [
      "Towers",
      "Exclusive Towers"
    ],
    "useful": true
  },
  {
    "count": 1,
    "name": "Swarmer",
    "category": [
      "Towers",
      "Exclusive Towers"
    ],
    "useful": true
  },
  {
    "count": 1,
    "name": "Warlock",
    "category": [
      "Towers",
      "Exclusive Towers"
    ],
    "useful": true
  },
  {
    "count": 1,
    "name": "Toxic Gunner",
    "category": [
      "Towers",
      "Exclusive Towers"
    ],
    "useful": true
  },
  {
    "count": 1,
    "name": "Elf Camp",
    "category": [
      "Towers",
      "Exclusive Towers"
    ],
    "useful": true
  },
  {
    "count": 1,
    "name": "Sledger",
    "category": [
      "Towers",
      "Exclusive Towers"
    ],
    "useful": true
  },
  {
    "count": 1,
    "name": "Archer",
    "category": [
      "Towers",
      "Exclusive Towers"
    ],
    "useful": true
  },
  {
    "count": 1,
    "name": "Frost Blaster",
    "category": [
      "Towers",
      "Exclusive Towers"
    ],
    "useful": true
  },
  {
    "count": 1,
    "name": "Cryomancer",
    "category": [
      "Towers",
      "Exclusive Towers"
    ],
    "useful": true
  },
  {
    "count": 1,
    "name": "Commando",
    "category": [
      "Towers",
      "Exclusive Towers"
    ],
    "useful": true
  },
  {
    "count": 1,
    "name": "Slasher",
    "category": [
      "Towers",
      "Exclusive Towers"
    ],
    "useful": true
  },
  {
    "count": 1,
    "name": "Executioner",
    "category": [
      "Towers",
      "Exclusive Towers"
    ],
    "useful": true
  },
  {
    "count": 1,
    "name": "Spotlight Tech",
    "category": [
      "Towers",
      "Exclusive Towers"
    ],
    "useful": true
  },
  {
    "count": 1,
    "name": "Timescale tickets",
    "category": [
      "Features"
      "Timescale tickets"
    ],
    "useful": true
  },
  {
    "count": 1,
    "name": "Common Consumables",
    "category": [
      "Consumables"
    ],
    "trap": true
  },
  {
    "count": 1,
    "name": "Uncommon Consumables",
    "category": [
      "Consumables"
    ],
    "trap": true
  },
  {
    "count": 1,
    "name": "Rare Consumables",
    "category": [
      "Consumables"
    ],
    "trap": true
  },
  {
    "count": 1,
    "name": "Epic Consumables",
    "category": [
      "Consumables"
    ],
    "trap": true
  },
  {
    "count": 1,
    "name": "Legendary Consumables",
    "category": [
      "Consumables"
    ],
    "trap": true
  },
  {
    "count": 1,
    "name": "Exclusive Consumables",
    "category": [
      "Consumables"
    ],
    "trap": true
  },
  {
    "count": 1,
    "name": "Auto Skip",
    "category": [
      "Features"
    ],
    "useful": true
  }
]
